YouTube_ff/Youtube_ff.py
YouTube_ff/__init__.py
YouTube_ff-0.0.4.dist-info/METADATA
YouTube_ff-0.0.4.dist-info/WHEEL
YouTube_ff-0.0.4.dist-info/top_level.txt
YouTube_ff-0.0.4.dist-info/RECORD
