Metadata-Version: 2.1
Name: YouTube-ff
Version: 0.0.4
Summary: A library which can be used to search youtube videos with ease.
Author: Srinath-N-Gudi
Author-email: srinathngudi11@gmail.com
License: UNKNOWN
Keywords: python,video,youtube,youtube video,youtube video search
Platform: UNKNOWN
Classifier: Development Status :: 1 - Planning
Classifier: Intended Audience :: Developers
Classifier: Programming Language :: Python :: 3
Classifier: Operating System :: Unix
Classifier: Operating System :: MacOS :: MacOS X
Classifier: Operating System :: Microsoft :: Windows
Requires-Dist: pytube
Requires-Dist: requests
